<?xml version="1.0" encoding="UTF-8" standalone="no"?><events>
<user><password>graham</password><role>CLERK</role><username>chloe</username></user><user><password>graham</password><role>CLERK</role><username>chloe</username></user><mail><volume>1</volume><origin>upper hutt</origin><destination>otaki</destination><weight>20</weight><priority>true</priority></mail><route><price>23.23</price><origin>Wellington                                        </origin><transport_type>LAND</transport_type><destination>Pretoria                                          </destination></route><route><price>222223.23</price><origin>Wellington                                        </origin><transport_type>LAND</transport_type><destination>Pretoria                                          </destination></route><route><price>23.23</price><origin>Wellington                                        </origin><transport_type>LAND</transport_type><destination>Pretoria                                          </destination></route><route><price>23.23</price><origin>Wellington                                        </origin><transport_type>LAND</transport_type><destination>Paris                                             </destination></route><user><password>john</password><role>MANAGER</role><username>john</username></user><user><password>smith</password><role>CLERK</role><username>smith</username></user><route><price>25.36</price><origin>Wellington                                        </origin><transport_type>AIR</transport_type><destination>Paris                                             </destination></route><route><price>26.99</price><origin>Wellington                                        </origin><transport_type>AIR</transport_type><destination>Paris                                             </destination></route></events>